encryptiontools/__init__.py
encryptiontools/encryption.py
encryptiontools/exceptions.py
encryptiontools/signature.py
encryptiontools/utils.py
encryptiontools-1.0.0.dist-info/LICENSE
encryptiontools-1.0.0.dist-info/METADATA
encryptiontools-1.0.0.dist-info/WHEEL
encryptiontools-1.0.0.dist-info/top_level.txt
encryptiontools-1.0.0.dist-info/RECORD
