Metadata-Version: 2.1
Name: encryptiontools
Version: 1.0.0
Summary: Tools for encryption and decryption, signing and verification. Use symmetric and asymmetric (RSA-based) encryption.
Home-page: https://github.com/Smoren/encryptiontools-pypi
Author: Smoren
Author-email: ofigate@gmail.com
Project-URL: Documentation, https://github.com/Smoren/encryptiontools-pypi
Project-URL: Bug Reports, https://github.com/Smoren/encryptiontools-pypi/issues
Project-URL: Source Code, https://github.com/Smoren/encryptiontools-pypi
Keywords: cryptography,encryption,rsa,signing,verification,symmetric,asymmetric
Classifier: Development Status :: 5 - Production/Stable
Classifier: Intended Audience :: Developers
Classifier: Topic :: Security :: Cryptography
Classifier: Programming Language :: Python :: 3
Classifier: Programming Language :: Python :: 3.7
Classifier: Programming Language :: Python :: 3.8
Classifier: Programming Language :: Python :: 3.9
Classifier: Programming Language :: Python :: 3.10
Classifier: Programming Language :: Python :: 3.11
Classifier: Programming Language :: Python :: 3 :: Only
Classifier: License :: OSI Approved :: MIT License
Classifier: Operating System :: OS Independent
Requires-Python: >=3.7
License-File: LICENSE
Requires-Dist: rsa
Requires-Dist: cryptography
Provides-Extra: dev
Requires-Dist: check-manifest ; extra == 'dev'
Requires-Dist: coverage ; extra == 'dev'
Provides-Extra: test
Requires-Dist: coverage ; extra == 'test'
